decorator_retry/__init__.py
decorator_retry/py.typed
decorator_retry-0.1.9.dist-info/METADATA
decorator_retry-0.1.9.dist-info/WHEEL
decorator_retry-0.1.9.dist-info/RECORD
