Metadata-Version: 2.1
Name: decorator-retry
Version: 0.1.9
Summary: Retry functions and async functions
Author: Yibo Mao
Author-email: yibo.mao@genscript.com
Requires-Python: >=3.8,<4.0
Classifier: Programming Language :: Python :: 3
Classifier: Programming Language :: Python :: 3.8
Classifier: Programming Language :: Python :: 3.9
Classifier: Programming Language :: Python :: 3.10
Classifier: Programming Language :: Python :: 3.11
Requires-Dist: typing-extensions (>=4.11.0,<5.0.0)
